featureeng/__init__.py
featureeng/featureeng.py
featureeng-0.1.0.dist-info/AUTHORS.rst
featureeng-0.1.0.dist-info/LICENSE
featureeng-0.1.0.dist-info/METADATA
featureeng-0.1.0.dist-info/WHEEL
featureeng-0.1.0.dist-info/top_level.txt
featureeng-0.1.0.dist-info/RECORD
