Metadata-Version: 2.1
Name: featureeng
Version: 0.1.0
Summary: A bunch of functions to enable and make FE easy when building Machine Learning Models
Home-page: https://github.com/Abuton/featureeng
Author: Abubakar Alaro
Author-email: alaroabubakarolayemi@yahoo.com
License: BSD license
Keywords: featureeng
Platform: UNKNOWN
Classifier: Development Status :: 2 - Pre-Alpha
Classifier: Intended Audience :: Developers
Classifier: License :: OSI Approved :: BSD License
Classifier: Natural Language :: English
Classifier: Programming Language :: Python :: 3
Classifier: Programming Language :: Python :: 3.6
Classifier: Programming Language :: Python :: 3.7
Classifier: Programming Language :: Python :: 3.8
Requires-Python: >=3.6
Requires-Dist: pandas (>=1.1.0)
Requires-Dist: numpy (>=1.19.0)
